odoo10_addon_product_attribute_set_completeness-10.0.1.2.0.99.dev5-py3.8-nspkg.pth
odoo/addons/product_attribute_set_completeness/README.rst
odoo/addons/product_attribute_set_completeness/__init__.py
odoo/addons/product_attribute_set_completeness/__manifest__.py
odoo/addons/product_attribute_set_completeness/components/__init__.py
odoo/addons/product_attribute_set_completeness/components/product_template_event_listener.py
odoo/addons/product_attribute_set_completeness/readme/CONTRIBUTORS.rst
odoo/addons/product_attribute_set_completeness/readme/DESCRIPTION.rst
odoo/addons/product_attribute_set_completeness/readme/USAGE.rst
odoo/addons/product_attribute_set_completeness/static/description/icon.png
odoo/addons/product_attribute_set_completeness/static/description/index.html
odoo/addons/product_attribute_set_completeness/views/product_template_view.xml
odoo10_addon_product_attribute_set_completeness-10.0.1.2.0.99.dev5.dist-info/METADATA
odoo10_addon_product_attribute_set_completeness-10.0.1.2.0.99.dev5.dist-info/WHEEL
odoo10_addon_product_attribute_set_completeness-10.0.1.2.0.99.dev5.dist-info/namespace_packages.txt
odoo10_addon_product_attribute_set_completeness-10.0.1.2.0.99.dev5.dist-info/top_level.txt
odoo10_addon_product_attribute_set_completeness-10.0.1.2.0.99.dev5.dist-info/RECORD
